ciscoisesdk/__init__.py
ciscoisesdk/_metadata.py
ciscoisesdk/api/__init__.py
ciscoisesdk/api/authentication.py
ciscoisesdk/api/custom_caller.py
ciscoisesdk/api/v3_1_0/__init__.py
ciscoisesdk/api/v3_1_0/aci_bindings.py
ciscoisesdk/api/v3_1_0/aci_settings.py
ciscoisesdk/api/v3_1_0/active_directory.py
ciscoisesdk/api/v3_1_0/admin_user.py
ciscoisesdk/api/v3_1_0/allowed_protocols.py
ciscoisesdk/api/v3_1_0/anc_endpoint.py
ciscoisesdk/api/v3_1_0/anc_policy.py
ciscoisesdk/api/v3_1_0/authorization_profile.py
ciscoisesdk/api/v3_1_0/backup_and_restore.py
ciscoisesdk/api/v3_1_0/byod_portal.py
ciscoisesdk/api/v3_1_0/certificate_profile.py
ciscoisesdk/api/v3_1_0/certificate_template.py
ciscoisesdk/api/v3_1_0/certificates.py
ciscoisesdk/api/v3_1_0/clear_threats_and_vulnerabilities.py
ciscoisesdk/api/v3_1_0/consumer.py
ciscoisesdk/api/v3_1_0/device_administration_authentication_rules.py
ciscoisesdk/api/v3_1_0/device_administration_authorization_exception_rules.py
ciscoisesdk/api/v3_1_0/device_administration_authorization_global_exception_rules.py
ciscoisesdk/api/v3_1_0/device_administration_authorization_rules.py
ciscoisesdk/api/v3_1_0/device_administration_command_set.py
ciscoisesdk/api/v3_1_0/device_administration_conditions.py
ciscoisesdk/api/v3_1_0/device_administration_dictionary_attributes_list.py
ciscoisesdk/api/v3_1_0/device_administration_identity_stores.py
ciscoisesdk/api/v3_1_0/device_administration_network_conditions.py
ciscoisesdk/api/v3_1_0/device_administration_policy_set.py
ciscoisesdk/api/v3_1_0/device_administration_profiles.py
ciscoisesdk/api/v3_1_0/device_administration_service_names.py
ciscoisesdk/api/v3_1_0/device_administration_time_date_conditions.py
ciscoisesdk/api/v3_1_0/downloadable_acl.py
ciscoisesdk/api/v3_1_0/egress_matrix_cell.py
ciscoisesdk/api/v3_1_0/endpoint.py
ciscoisesdk/api/v3_1_0/endpoint_certificate.py
ciscoisesdk/api/v3_1_0/endpoint_identity_group.py
ciscoisesdk/api/v3_1_0/external_radius_server.py
ciscoisesdk/api/v3_1_0/filter_policy.py
ciscoisesdk-2.1.2.dist-info/LICENSE
ciscoisesdk-2.1.2.dist-info/METADATA
ciscoisesdk-2.1.2.dist-info/WHEEL
ciscoisesdk-2.1.2.dist-info/RECORD
