Metadata-Version: 2.1
Name: ciscoisesdk
Version: 2.1.2
Summary: Cisco Identity Services Engine Platform SDK
Home-page: https://ciscoisesdk.readthedocs.io/en/latest/
License: MIT
Keywords: Cisco,Identity Services Engine,SDK
Author: Jose Bogarin Solano
Author-email: jbogarin@cloverhound.com
Requires-Python: >=3.6,<4.0
Classifier: License :: OSI Approved :: MIT License
Classifier: Programming Language :: Python :: 3
Classifier: Programming Language :: Python :: 3.6
Classifier: Programming Language :: Python :: 3.7
Classifier: Programming Language :: Python :: 3.8
Classifier: Programming Language :: Python :: 3.9
Classifier: Programming Language :: Python :: 3.10
Classifier: Programming Language :: Python :: 3.11
Requires-Dist: fastjsonschema (>=2.16.2,<3.0.0)
Requires-Dist: future (>=0.18.3,<0.19.0)
Requires-Dist: requests (>=2.27.1,<=2.28)
Requires-Dist: requests-toolbelt (>=1.0.0,<2.0.0)
Requires-Dist: xmltodict (==0.12.0)
Project-URL: Repository, https://github.com/CiscoISE/ciscoisesdk
